<?xml version="1.0" encoding="UTF-8"?>
<OfficeApp
  xmlns="http://schemas.microsoft.com/office/appforoffice/1.1"
  xmlns:xsi="http://www.w3.org/2001/XMLSchema-instance"
  xmlns:bt="http://schemas.microsoft.com/office/officeappbasictypes/1.0"
  xmlns:ov="http://schemas.microsoft.com/office/taskpaneappversionoverrides"
  xsi:type="TaskPaneApp">

  <Id>a7c1e3f0-4b2d-4e8a-9f6c-1d3e5a7b9c0d</Id>
  <Version>1.0.0.0</Version>
  <ProviderName>German Foundations</ProviderName>
  <DefaultLocale>en-US</DefaultLocale>
  <DisplayName DefaultValue="GF Sort" />
  <Description DefaultValue="Sort noun-group sections in the German Foundations Resource Guide." />
  <IconUrl DefaultValue="https://localhost:3000/assets/icon-32.png" />
  <HighResolutionIconUrl DefaultValue="https://localhost:3000/assets/icon-80.png" />
  <SupportUrl DefaultValue="https://localhost:3000/" />

  <Hosts>
    <Host Name="Document" />
  </Hosts>

  <Requirements>
    <Sets>
      <Set Name="WordApi" MinVersion="1.3" />
    </Sets>
  </Requirements>

  <DefaultSettings>
    <SourceLocation DefaultValue="https://localhost:3000/taskpane.html" />
  </DefaultSettings>

  <Permissions>ReadWriteDocument</Permissions>

  <VersionOverrides
    xmlns="http://schemas.microsoft.com/office/taskpaneappversionoverrides"
    xsi:type="VersionOverridesV1_0">

    <Hosts>
      <Host xsi:type="Document">
        <DesktopFormFactor>
          <ExtensionPoint xsi:type="PrimaryCommandSurface">
            <OfficeTab id="TabHome">
              <Group id="GFGroup">
                <Label resid="groupLabel" />
                <Icon>
                  <bt:Image size="16" resid="icon16" />
                  <bt:Image size="32" resid="icon32" />
                  <bt:Image size="80" resid="icon80" />
                </Icon>
                <Control xsi:type="Button" id="sortButton">
                  <Label resid="sortButtonLabel" />
                  <Supertip>
                    <Title resid="sortButtonLabel" />
                    <Description resid="sortButtonTip" />
                  </Supertip>
                  <Icon>
                    <bt:Image size="16" resid="icon16" />
                    <bt:Image size="32" resid="icon32" />
                    <bt:Image size="80" resid="icon80" />
                  </Icon>
                  <Action xsi:type="ShowTaskpane">
                    <TaskpaneId>GFTaskpane</TaskpaneId>
                    <SourceLocation resid="taskpaneUrl" />
                  </Action>
                </Control>
              </Group>
            </OfficeTab>
          </ExtensionPoint>
        </DesktopFormFactor>
      </Host>
    </Hosts>

    <Resources>
      <bt:Images>
        <bt:Image id="icon16" DefaultValue="https://localhost:3000/assets/icon-16.png" />
        <bt:Image id="icon32" DefaultValue="https://localhost:3000/assets/icon-32.png" />
        <bt:Image id="icon80" DefaultValue="https://localhost:3000/assets/icon-80.png" />
      </bt:Images>
      <bt:Urls>
        <bt:Url id="taskpaneUrl" DefaultValue="https://localhost:3000/taskpane.html" />
      </bt:Urls>
      <bt:ShortStrings>
        <bt:String id="groupLabel" DefaultValue="German Foundations" />
        <bt:String id="sortButtonLabel" DefaultValue="GF Sort" />
      </bt:ShortStrings>
      <bt:LongStrings>
        <bt:String id="sortButtonTip" DefaultValue="Open the sorting panel to sort noun-group sections by the German Foundations design principles." />
      </bt:LongStrings>
    </Resources>
  </VersionOverrides>
</OfficeApp>
